{
  "posts": [
    {
      "id": 1,
      "username": "alex_photo",
      "userAvatar": "https://picsum.photos/seed/user1/100/100",
      "imageUrl": "https://picsum.photos/seed/post1/600/600",
      "caption": "Beautiful sunset at the beach 🌅",
      "likes": 342,
      "timestamp": "2025-10-07T18:30:00Z",
      "comments": [
        {
          "id": 1,
          "username": "sarah_m",
          "text": "Stunning shot!",
          "timestamp": "2025-10-07T19:00:00Z"
        },
        {
          "id": 2,
          "username": "mike_travel",
          "text": "Where is this?",
          "timestamp": "2025-10-07T19:15:00Z"
        }
      ]
    },
    {
      "id": 2,
      "username": "foodie_jenny",
      "userAvatar": "https://picsum.photos/seed/user2/100/100",
      "imageUrl": "https://picsum.photos/seed/post2/600/600",
      "caption": "Best pasta in town! 🍝",
      "likes": 521,
      "timestamp": "2025-10-07T12:15:00Z",
      "comments": [
        {
          "id": 3,
          "username": "chef_mario",
          "text": "Looks delicious!",
          "timestamp": "2025-10-07T13:00:00Z"
        }
      ]
    },
    {
      "id": 3,
      "username": "travel_chris",
      "userAvatar": "https://picsum.photos/seed/user3/100/100",
      "imageUrl": "https://picsum.photos/seed/post3/600/600",
      "caption": "Mountain views never get old ⛰️",
      "likes": 892,
      "timestamp": "2025-10-06T08:45:00Z",
      "comments": []
    },
    {
      "id": 4,
      "username": "design_emma",
      "userAvatar": "https://picsum.photos/seed/user4/100/100",
      "imageUrl": "https://picsum.photos/seed/post4/600/600",
      "caption": "New workspace setup 💻✨",
      "likes": 234,
      "timestamp": "2025-10-06T16:20:00Z",
      "comments": [
        {
          "id": 4,
          "username": "tech_david",
          "text": "Clean setup!",
          "timestamp": "2025-10-06T17:00:00Z"
        },
        {
          "id": 5,
          "username": "workspace_ideas",
          "text": "Love the minimalist style",
          "timestamp": "2025-10-06T18:30:00Z"
        }
      ]
    },
    {
      "id": 5,
      "username": "fitness_mark",
      "userAvatar": "https://picsum.photos/seed/user5/100/100",
      "imageUrl": "https://picsum.photos/seed/post5/600/600",
      "caption": "Morning run completed! 💪 #fitness",
      "likes": 445,
      "timestamp": "2025-10-05T06:30:00Z",
      "comments": [
        {
          "id": 6,
          "username": "run_club",
          "text": "Great pace!",
          "timestamp": "2025-10-05T07:00:00Z"
        }
      ]
    },
    {
      "id": 6,
      "username": "art_sophia",
      "userAvatar": "https://picsum.photos/seed/user6/100/100",
      "imageUrl": "https://picsum.photos/seed/post6/600/600",
      "caption": "Latest painting finished 🎨",
      "likes": 678,
      "timestamp": "2025-10-05T14:00:00Z",
      "comments": [
        {
          "id": 7,
          "username": "gallery_nyc",
          "text": "Beautiful work!",
          "timestamp": "2025-10-05T15:00:00Z"
        }
      ]
    },
    {
      "id": 7,
      "username": "coffee_lover",
      "userAvatar": "https://picsum.photos/seed/user7/100/100",
      "imageUrl": "https://picsum.photos/seed/post7/600/600",
      "caption": "Perfect latte art ☕",
      "likes": 312,
      "timestamp": "2025-10-04T09:00:00Z",
      "comments": []
    },
    {
      "id": 8,
      "username": "pet_life",
      "userAvatar": "https://picsum.photos/seed/user8/100/100",
      "imageUrl": "https://picsum.photos/seed/post8/600/600",
      "caption": "Meet my new puppy! 🐕",
      "likes": 1243,
      "timestamp": "2025-10-04T11:30:00Z",
      "comments": [
        {
          "id": 8,
          "username": "dog_lovers",
          "text": "So cute!",
          "timestamp": "2025-10-04T12:00:00Z"
        },
        {
          "id": 9,
          "username": "pets_daily",
          "text": "What's the name?",
          "timestamp": "2025-10-04T12:30:00Z"
        }
      ]
    },
    {
      "id": 9,
      "username": "nature_tom",
      "userAvatar": "https://picsum.photos/seed/user9/100/100",
      "imageUrl": "https://picsum.photos/seed/post9/600/600",
      "caption": "Forest therapy 🌲🌿",
      "likes": 567,
      "timestamp": "2025-10-03T15:45:00Z",
      "comments": [
        {
          "id": 10,
          "username": "hiking_trails",
          "text": "Which trail is this?",
          "timestamp": "2025-10-03T16:00:00Z"
        }
      ]
    },
    {
      "id": 10,
      "username": "street_photo",
      "userAvatar": "https://picsum.photos/seed/user10/100/100",
      "imageUrl": "https://picsum.photos/seed/post10/600/600",
      "caption": "City lights at night 🌃",
      "likes": 789,
      "timestamp": "2025-10-03T20:00:00Z",
      "comments": [
        {
          "id": 11,
          "username": "urban_explorer",
          "text": "Amazing composition!",
          "timestamp": "2025-10-03T21:00:00Z"
        }
      ]
    },
    {
      "id": 11,
      "username": "yoga_lisa",
      "userAvatar": "https://picsum.photos/seed/user11/100/100",
      "imageUrl": "https://picsum.photos/seed/post11/600/600",
      "caption": "Morning yoga session 🧘‍♀️",
      "likes": 456,
      "timestamp": "2025-10-03T07:00:00Z",
      "comments": []
    },
    {
      "id": 12,
      "username": "music_dan",
      "userAvatar": "https://picsum.photos/seed/user12/100/100",
      "imageUrl": "https://picsum.photos/seed/post12/600/600",
      "caption": "Studio session vibes 🎸",
      "likes": 623,
      "timestamp": "2025-10-02T22:30:00Z",
      "comments": [
        {
          "id": 12,
          "username": "guitar_lessons",
          "text": "Sounds amazing!",
          "timestamp": "2025-10-02T23:00:00Z"
        }
      ]
    },
    {
      "id": 13,
      "username": "baker_amy",
      "userAvatar": "https://picsum.photos/seed/user13/100/100",
      "imageUrl": "https://picsum.photos/seed/post13/600/600",
      "caption": "Fresh croissants this morning 🥐",
      "likes": 891,
      "timestamp": "2025-10-02T06:45:00Z",
      "comments": [
        {
          "id": 13,
          "username": "breakfast_club",
          "text": "These look perfect!",
          "timestamp": "2025-10-02T07:30:00Z"
        },
        {
          "id": 14,
          "username": "foodie_jenny",
          "text": "Recipe please!",
          "timestamp": "2025-10-02T08:00:00Z"
        }
      ]
    },
    {
      "id": 14,
      "username": "book_reader",
      "userAvatar": "https://picsum.photos/seed/user14/100/100",
      "imageUrl": "https://picsum.photos/seed/post14/600/600",
      "caption": "Cozy reading corner 📚",
      "likes": 334,
      "timestamp": "2025-10-01T19:00:00Z",
      "comments": []
    },
    {
      "id": 15,
      "username": "adventure_sam",
      "userAvatar": "https://picsum.photos/seed/user15/100/100",
      "imageUrl": "https://picsum.photos/seed/post15/600/600",
      "caption": "Cliff diving today! 🌊",
      "likes": 1122,
      "timestamp": "2025-10-01T14:20:00Z",
      "comments": [
        {
          "id": 15,
          "username": "extreme_sports",
          "text": "Epic jump!",
          "timestamp": "2025-10-01T15:00:00Z"
        }
      ]
    },
    {
      "id": 16,
      "username": "garden_grace",
      "userAvatar": "https://picsum.photos/seed/user16/100/100",
      "imageUrl": "https://picsum.photos/seed/post16/600/600",
      "caption": "My roses are blooming 🌹",
      "likes": 445,
      "timestamp": "2025-09-30T10:15:00Z",
      "comments": [
        {
          "id": 16,
          "username": "plant_tips",
          "text": "Beautiful colors!",
          "timestamp": "2025-09-30T11:00:00Z"
        }
      ]
    },
    {
      "id": 17,
      "username": "tech_brian",
      "userAvatar": "https://picsum.photos/seed/user17/100/100",
      "imageUrl": "https://picsum.photos/seed/post17/600/600",
      "caption": "New MacBook setup complete 💻",
      "likes": 778,
      "timestamp": "2025-09-30T16:45:00Z",
      "comments": []
    },
    {
      "id": 18,
      "username": "fashion_kate",
      "userAvatar": "https://picsum.photos/seed/user18/100/100",
      "imageUrl": "https://picsum.photos/seed/post18/600/600",
      "caption": "Fall fashion lookbook 🍂",
      "likes": 1567,
      "timestamp": "2025-09-29T13:00:00Z",
      "comments": [
        {
          "id": 17,
          "username": "style_daily",
          "text": "Love this outfit!",
          "timestamp": "2025-09-29T14:00:00Z"
        },
        {
          "id": 18,
          "username": "fashion_trends",
          "text": "Where's the jacket from?",
          "timestamp": "2025-09-29T15:00:00Z"
        }
      ]
    },
    {
      "id": 19,
      "username": "skate_mike",
      "userAvatar": "https://picsum.photos/seed/user19/100/100",
      "imageUrl": "https://picsum.photos/seed/post19/600/600",
      "caption": "Landed my first kickflip! 🛹",
      "likes": 923,
      "timestamp": "2025-09-29T17:30:00Z",
      "comments": [
        {
          "id": 19,
          "username": "skate_crew",
          "text": "Clean landing!",
          "timestamp": "2025-09-29T18:00:00Z"
        }
      ]
    },
    {
      "id": 20,
      "username": "ocean_diver",
      "userAvatar": "https://picsum.photos/seed/user20/100/100",
      "imageUrl": "https://picsum.photos/seed/post20/600/600",
      "caption": "Underwater paradise 🐠",
      "likes": 2341,
      "timestamp": "2025-09-28T11:00:00Z",
      "comments": [
        {
          "id": 20,
          "username": "dive_life",
          "text": "Amazing visibility!",
          "timestamp": "2025-09-28T12:00:00Z"
        },
        {
          "id": 21,
          "username": "marine_bio",
          "text": "What species did you see?",
          "timestamp": "2025-09-28T13:00:00Z"
        }
      ]
    },
    {
      "id": 21,
      "username": "chef_ricardo",
      "userAvatar": "https://picsum.photos/seed/user21/100/100",
      "imageUrl": "https://picsum.photos/seed/post21/600/600",
      "caption": "Tonight's special: Grilled salmon 🍽️",
      "likes": 687,
      "timestamp": "2025-09-28T19:00:00Z",
      "comments": []
    },
    {
      "id": 22,
      "username": "dance_maria",
      "userAvatar": "https://picsum.photos/seed/user22/100/100",
      "imageUrl": "https://picsum.photos/seed/post22/600/600",
      "caption": "Ballet practice never stops 🩰",
      "likes": 534,
      "timestamp": "2025-09-27T15:30:00Z",
      "comments": [
        {
          "id": 22,
          "username": "ballet_world",
          "text": "Beautiful form!",
          "timestamp": "2025-09-27T16:00:00Z"
        }
      ]
    },
    {
      "id": 23,
      "username": "wildlife_joe",
      "userAvatar": "https://picsum.photos/seed/user23/100/100",
      "imageUrl": "https://picsum.photos/seed/post23/600/600",
      "caption": "Spotted a rare bird today 🦜",
      "likes": 1890,
      "timestamp": "2025-09-27T08:20:00Z",
      "comments": [
        {
          "id": 23,
          "username": "bird_watchers",
          "text": "Great shot!",
          "timestamp": "2025-09-27T09:00:00Z"
        }
      ]
    },
    {
      "id": 24,
      "username": "pottery_lynn",
      "userAvatar": "https://picsum.photos/seed/user24/100/100",
      "imageUrl": "https://picsum.photos/seed/post24/600/600",
      "caption": "New ceramic collection 🏺",
      "likes": 456,
      "timestamp": "2025-09-26T14:00:00Z",
      "comments": []
    },
    {
      "id": 25,
      "username": "surf_jake",
      "userAvatar": "https://picsum.photos/seed/user25/100/100",
      "imageUrl": "https://picsum.photos/seed/post25/600/600",
      "caption": "Perfect waves this morning 🏄‍♂️",
      "likes": 1234,
      "timestamp": "2025-09-26T06:30:00Z",
      "comments": [
        {
          "id": 24,
          "username": "surf_report",
          "text": "Conditions look perfect!",
          "timestamp": "2025-09-26T07:00:00Z"
        },
        {
          "id": 25,
          "username": "beach_life",
          "text": "Jealous!",
          "timestamp": "2025-09-26T08:00:00Z"
        }
      ]
    },
    {
      "id": 26,
      "username": "astro_sarah",
      "userAvatar": "https://picsum.photos/seed/user26/100/100",
      "imageUrl": "https://picsum.photos/seed/post26/600/600",
      "caption": "Milky Way captured last night ✨",
      "likes": 3456,
      "timestamp": "2025-09-25T23:45:00Z",
      "comments": [
        {
          "id": 26,
          "username": "space_lovers",
          "text": "Incredible!",
          "timestamp": "2025-09-26T00:30:00Z"
        }
      ]
    },
    {
      "id": 27,
      "username": "cycling_tom",
      "userAvatar": "https://picsum.photos/seed/user27/100/100",
      "imageUrl": "https://picsum.photos/seed/post27/600/600",
      "caption": "50km ride completed! 🚴‍♂️",
      "likes": 567,
      "timestamp": "2025-09-25T17:00:00Z",
      "comments": []
    },
    {
      "id": 28,
      "username": "architecture_anna",
      "userAvatar": "https://picsum.photos/seed/user28/100/100",
      "imageUrl": "https://picsum.photos/seed/post28/600/600",
      "caption": "Modern design inspiration 🏢",
      "likes": 890,
      "timestamp": "2025-09-25T12:30:00Z",
      "comments": [
        {
          "id": 27,
          "username": "design_daily",
          "text": "Love the lines!",
          "timestamp": "2025-09-25T13:00:00Z"
        }
      ]
    },
    {
      "id": 29,
      "username": "cocktail_kevin",
      "userAvatar": "https://picsum.photos/seed/user29/100/100",
      "imageUrl": "https://picsum.photos/seed/post29/600/600",
      "caption": "Signature mojito recipe 🍹",
      "likes": 723,
      "timestamp": "2025-09-24T20:00:00Z",
      "comments": [
        {
          "id": 28,
          "username": "bar_life",
          "text": "Perfect balance!",
          "timestamp": "2025-09-24T21:00:00Z"
        }
      ]
    },
    {
      "id": 30,
      "username": "vintage_rachel",
      "userAvatar": "https://picsum.photos/seed/user30/100/100",
      "imageUrl": "https://picsum.photos/seed/post30/600/600",
      "caption": "Thrift store finds 👗",
      "likes": 945,
      "timestamp": "2025-09-24T15:20:00Z",
      "comments": []
    },
    {
      "id": 31,
      "username": "climbing_alex",
      "userAvatar": "https://picsum.photos/seed/user31/100/100",
      "imageUrl": "https://picsum.photos/seed/post31/600/600",
      "caption": "Conquered this route today! 🧗",
      "likes": 1456,
      "timestamp": "2025-09-23T16:45:00Z",
      "comments": [
        {
          "id": 29,
          "username": "climb_crew",
          "text": "That's a tough one!",
          "timestamp": "2025-09-23T17:30:00Z"
        }
      ]
    },
    {
      "id": 32,
      "username": "vegan_meals",
      "userAvatar": "https://picsum.photos/seed/user32/100/100",
      "imageUrl": "https://picsum.photos/seed/post32/600/600",
      "caption": "Plant-based Buddha bowl 🥗",
      "likes": 812,
      "timestamp": "2025-09-23T12:00:00Z",
      "comments": [
        {
          "id": 30,
          "username": "healthy_eats",
          "text": "Recipe?",
          "timestamp": "2025-09-23T13:00:00Z"
        }
      ]
    },
    {
      "id": 33,
      "username": "drone_pilot",
      "userAvatar": "https://picsum.photos/seed/user33/100/100",
      "imageUrl": "https://picsum.photos/seed/post33/600/600",
      "caption": "Aerial view of the city 🚁",
      "likes": 2134,
      "timestamp": "2025-09-22T18:30:00Z",
      "comments": []
    },
    {
      "id": 34,
      "username": "painting_studio",
      "userAvatar": "https://picsum.photos/seed/user34/100/100",
      "imageUrl": "https://picsum.photos/seed/post34/600/600",
      "caption": "Abstract series continues 🎨",
      "likes": 678,
      "timestamp": "2025-09-22T10:15:00Z",
      "comments": [
        {
          "id": 31,
          "username": "art_gallery",
          "text": "Stunning piece!",
          "timestamp": "2025-09-22T11:00:00Z"
        }
      ]
    },
    {
      "id": 35,
      "username": "gaming_leo",
      "userAvatar": "https://picsum.photos/seed/user35/100/100",
      "imageUrl": "https://picsum.photos/seed/post35/600/600",
      "caption": "New gaming setup complete! 🎮",
      "likes": 1890,
      "timestamp": "2025-09-21T21:00:00Z",
      "comments": [
        {
          "id": 32,
          "username": "pc_builds",
          "text": "What specs?",
          "timestamp": "2025-09-21T22:00:00Z"
        }
      ]
    },
    {
      "id": 36,
      "username": "home_decor",
      "userAvatar": "https://picsum.photos/seed/user36/100/100",
      "imageUrl": "https://picsum.photos/seed/post36/600/600",
      "caption": "Living room makeover 🛋️",
      "likes": 1234,
      "timestamp": "2025-09-21T14:30:00Z",
      "comments": []
    },
    {
      "id": 37,
      "username": "morning_coffee",
      "userAvatar": "https://picsum.photos/seed/user37/100/100",
      "imageUrl": "https://picsum.photos/seed/post37/600/600",
      "caption": "Sunday morning ritual ☕",
      "likes": 456,
      "timestamp": "2025-09-21T08:00:00Z",
      "comments": [
        {
          "id": 33,
          "username": "cafe_culture",
          "text": "Perfect pour over!",
          "timestamp": "2025-09-21T09:00:00Z"
        }
      ]
    },
    {
      "id": 38,
      "username": "marathon_runner",
      "userAvatar": "https://picsum.photos/seed/user38/100/100",
      "imageUrl": "https://picsum.photos/seed/post38/600/600",
      "caption": "Marathon training week 8 🏃",
      "likes": 789,
      "timestamp": "2025-09-20T06:00:00Z",
      "comments": [
        {
          "id": 34,
          "username": "running_coach",
          "text": "Keep it up!",
          "timestamp": "2025-09-20T07:00:00Z"
        }
      ]
    },
    {
      "id": 39,
      "username": "street_art",
      "userAvatar": "https://picsum.photos/seed/user39/100/100",
      "imageUrl": "https://picsum.photos/seed/post39/600/600",
      "caption": "Found this amazing mural 🎨",
      "likes": 1567,
      "timestamp": "2025-09-20T16:20:00Z",
      "comments": []
    },
    {
      "id": 40,
      "username": "meditation_zen",
      "userAvatar": "https://picsum.photos/seed/user40/100/100",
      "imageUrl": "https://picsum.photos/seed/post40/600/600",
      "caption": "Peace and mindfulness 🧘",
      "likes": 923,
      "timestamp": "2025-09-19T07:30:00Z",
      "comments": [
        {
          "id": 35,
          "username": "wellness_tips",
          "text": "Beautiful space!",
          "timestamp": "2025-09-19T08:00:00Z"
        }
      ]
    },
    {
      "id": 41,
      "username": "car_enthusiast",
      "userAvatar": "https://picsum.photos/seed/user41/100/100",
      "imageUrl": "https://picsum.photos/seed/post41/600/600",
      "caption": "Classic car show today 🚗",
      "likes": 2456,
      "timestamp": "2025-09-19T13:00:00Z",
      "comments": [
        {
          "id": 36,
          "username": "vintage_cars",
          "text": "Dream car!",
          "timestamp": "2025-09-19T14:00:00Z"
        }
      ]
    },
    {
      "id": 42,
      "username": "flowers_bloom",
      "userAvatar": "https://picsum.photos/seed/user42/100/100",
      "imageUrl": "https://picsum.photos/seed/post42/600/600",
      "caption": "Spring is coming 🌸",
      "likes": 1123,
      "timestamp": "2025-09-18T10:45:00Z",
      "comments": []
    },
    {
      "id": 43,
      "username": "macro_lens",
      "userAvatar": "https://picsum.photos/seed/user43/100/100",
      "imageUrl": "https://picsum.photos/seed/post43/600/600",
      "caption": "Macro photography magic 📸",
      "likes": 1678,
      "timestamp": "2025-09-18T15:30:00Z",
      "comments": [
        {
          "id": 37,
          "username": "photo_gear",
          "text": "What lens?",
          "timestamp": "2025-09-18T16:00:00Z"
        }
      ]
    },
    {
      "id": 44,
      "username": "backpacking_life",
      "userAvatar": "https://picsum.photos/seed/user44/100/100",
      "imageUrl": "https://picsum.photos/seed/post44/600/600",
      "caption": "Off the grid for a week 🎒",
      "likes": 2890,
      "timestamp": "2025-09-17T09:00:00Z",
      "comments": [
        {
          "id": 38,
          "username": "outdoor_gear",
          "text": "Stay safe!",
          "timestamp": "2025-09-17T10:00:00Z"
        }
      ]
    },
    {
      "id": 45,
      "username": "dessert_queen",
      "userAvatar": "https://picsum.photos/seed/user45/100/100",
      "imageUrl": "https://picsum.photos/seed/post45/600/600",
      "caption": "Homemade cheesecake 🍰",
      "likes": 1456,
      "timestamp": "2025-09-17T19:00:00Z",
      "comments": [
        {
          "id": 39,
          "username": "sweet_tooth",
          "text": "Looks amazing!",
          "timestamp": "2025-09-17T20:00:00Z"
        }
      ]
    },
    {
      "id": 46,
      "username": "minimalist_home",
      "userAvatar": "https://picsum.photos/seed/user46/100/100",
      "imageUrl": "https://picsum.photos/seed/post46/600/600",
      "caption": "Less is more ✨",
      "likes": 890,
      "timestamp": "2025-09-16T11:30:00Z",
      "comments": []
    },
    {
      "id": 47,
      "username": "film_buff",
      "userAvatar": "https://picsum.photos/seed/user47/100/100",
      "imageUrl": "https://picsum.photos/seed/post47/600/600",
      "caption": "Movie night essentials 🎬",
      "likes": 567,
      "timestamp": "2025-09-16T20:00:00Z",
      "comments": [
        {
          "id": 40,
          "username": "cinema_club",
          "text": "What are you watching?",
          "timestamp": "2025-09-16T21:00:00Z"
        }
      ]
    },
    {
      "id": 48,
      "username": "snowboard_sam",
      "userAvatar": "https://picsum.photos/seed/user48/100/100",
      "imageUrl": "https://picsum.photos/seed/post48/600/600",
      "caption": "First powder day! ❄️",
      "likes": 1890,
      "timestamp": "2025-09-15T08:30:00Z",
      "comments": [
        {
          "id": 41,
          "username": "mountain_life",
          "text": "Epic conditions!",
          "timestamp": "2025-09-15T09:00:00Z"
        }
      ]
    },
    {
      "id": 49,
      "username": "calligraphy_art",
      "userAvatar": "https://picsum.photos/seed/user49/100/100",
      "imageUrl": "https://picsum.photos/seed/post49/600/600",
      "caption": "Hand lettering practice ✍️",
      "likes": 723,
      "timestamp": "2025-09-15T14:00:00Z",
      "comments": []
    },
    {
      "id": 50,
      "username": "city_skyline",
      "userAvatar": "https://picsum.photos/seed/user50/100/100",
      "imageUrl": "https://picsum.photos/seed/post50/600/600",
      "caption": "Golden hour magic 🌆",
      "likes": 3456,
      "timestamp": "2025-09-14T18:45:00Z",
      "comments": [
        {
          "id": 42,
          "username": "urban_photos",
          "text": "Perfect timing!",
          "timestamp": "2025-09-14T19:30:00Z"
        }
      ]
    },
    {
      "id": 51,
      "username": "aquarium_life",
      "userAvatar": "https://picsum.photos/seed/user51/100/100",
      "imageUrl": "https://picsum.photos/seed/post51/600/600",
      "caption": "New tank setup complete 🐟",
      "likes": 567,
      "timestamp": "2025-09-14T12:00:00Z",
      "comments": [
        {
          "id": 43,
          "username": "fish_keeper",
          "text": "Beautiful aquascape!",
          "timestamp": "2025-09-14T13:00:00Z"
        }
      ]
    },
    {
      "id": 52,
      "username": "woodworking_pro",
      "userAvatar": "https://picsum.photos/seed/user52/100/100",
      "imageUrl": "https://picsum.photos/seed/post52/600/600",
      "caption": "Custom dining table finished 🪵",
      "likes": 1234,
      "timestamp": "2025-09-13T16:30:00Z",
      "comments": []
    },
    {
      "id": 53,
      "username": "tea_ceremony",
      "userAvatar": "https://picsum.photos/seed/user53/100/100",
      "imageUrl": "https://picsum.photos/seed/post53/600/600",
      "caption": "Afternoon tea ritual 🍵",
      "likes": 445,
      "timestamp": "2025-09-13T15:00:00Z",
      "comments": [
        {
          "id": 44,
          "username": "tea_lovers",
          "text": "What blend?",
          "timestamp": "2025-09-13T16:00:00Z"
        }
      ]
    },
    {
      "id": 54,
      "username": "skateboard_tricks",
      "userAvatar": "https://picsum.photos/seed/user54/100/100",
      "imageUrl": "https://picsum.photos/seed/post54/600/600",
      "caption": "New trick learned! 🛹",
      "likes": 890,
      "timestamp": "2025-09-12T17:45:00Z",
      "comments": [
        {
          "id": 45,
          "username": "skate_park",
          "text": "Smooth!",
          "timestamp": "2025-09-12T18:30:00Z"
        }
      ]
    },
    {
      "id": 55,
      "username": "mountain_hiking",
      "userAvatar": "https://picsum.photos/seed/user55/100/100",
      "imageUrl": "https://picsum.photos/seed/post55/600/600",
      "caption": "Summit reached! ⛰️",
      "likes": 2567,
      "timestamp": "2025-09-12T11:00:00Z",
      "comments": []
    },
    {
      "id": 56,
      "username": "jazz_nights",
      "userAvatar": "https://picsum.photos/seed/user56/100/100",
      "imageUrl": "https://picsum.photos/seed/post56/600/600",
      "caption": "Live jazz performance 🎷",
      "likes": 1123,
      "timestamp": "2025-09-11T22:00:00Z",
      "comments": [
        {
          "id": 46,
          "username": "music_venue",
          "text": "Great show!",
          "timestamp": "2025-09-11T23:00:00Z"
        }
      ]
    },
    {
      "id": 57,
      "username": "landscape_views",
      "userAvatar": "https://picsum.photos/seed/user57/100/100",
      "imageUrl": "https://picsum.photos/seed/post57/600/600",
      "caption": "Nature's masterpiece 🏞️",
      "likes": 1890,
      "timestamp": "2025-09-11T14:30:00Z",
      "comments": [
        {
          "id": 47,
          "username": "nature_lovers",
          "text": "Breathtaking!",
          "timestamp": "2025-09-11T15:00:00Z"
        }
      ]
    },
    {
      "id": 58,
      "username": "cocktail_master",
      "userAvatar": "https://picsum.photos/seed/user58/100/100",
      "imageUrl": "https://picsum.photos/seed/post58/600/600",
      "caption": "Craft cocktail creation 🍸",
      "likes": 678,
      "timestamp": "2025-09-10T19:00:00Z",
      "comments": []
    },
    {
      "id": 59,
      "username": "urban_gardening",
      "userAvatar": "https://picsum.photos/seed/user59/100/100",
      "imageUrl": "https://picsum.photos/seed/post59/600/600",
      "caption": "Balcony garden thriving 🌿",
      "likes": 945,
      "timestamp": "2025-09-10T10:15:00Z",
      "comments": [
        {
          "id": 48,
          "username": "green_thumb",
          "text": "Tips please!",
          "timestamp": "2025-09-10T11:00:00Z"
        }
      ]
    },
    {
      "id": 60,
      "username": "abstract_painter",
      "userAvatar": "https://picsum.photos/seed/user60/100/100",
      "imageUrl": "https://picsum.photos/seed/post60/600/600",
      "caption": "New canvas completed 🎨",
      "likes": 1234,
      "timestamp": "2025-09-09T16:00:00Z",
      "comments": [
        {
          "id": 49,
          "username": "art_studio",
          "text": "Bold colors!",
          "timestamp": "2025-09-09T17:00:00Z"
        }
      ]
    },
    {
      "id": 61,
      "username": "motorcycle_rider",
      "userAvatar": "https://picsum.photos/seed/user61/100/100",
      "imageUrl": "https://picsum.photos/seed/post61/600/600",
      "caption": "Weekend ride through the canyon 🏍️",
      "likes": 1567,
      "timestamp": "2025-09-09T08:30:00Z",
      "comments": []
    },
    {
      "id": 62,
      "username": "sushi_chef",
      "userAvatar": "https://picsum.photos/seed/user62/100/100",
      "imageUrl": "https://picsum.photos/seed/post62/600/600",
      "caption": "Fresh sushi platter 🍣",
      "likes": 2134,
      "timestamp": "2025-09-08T18:00:00Z",
      "comments": [
        {
          "id": 50,
          "username": "food_critic",
          "text": "Presentation is perfect!",
          "timestamp": "2025-09-08T19:00:00Z"
        }
      ]
    },
    {
      "id": 63,
      "username": "vinyl_collector",
      "userAvatar": "https://picsum.photos/seed/user63/100/100",
      "imageUrl": "https://picsum.photos/seed/post63/600/600",
      "caption": "Latest record finds 🎵",
      "likes": 723,
      "timestamp": "2025-09-08T14:20:00Z",
      "comments": [
        {
          "id": 51,
          "username": "music_collector",
          "text": "Great collection!",
          "timestamp": "2025-09-08T15:00:00Z"
        }
      ]
    },
    {
      "id": 64,
      "username": "kayak_adventures",
      "userAvatar": "https://picsum.photos/seed/user64/100/100",
      "imageUrl": "https://picsum.photos/seed/post64/600/600",
      "caption": "Peaceful morning paddle 🛶",
      "likes": 1456,
      "timestamp": "2025-09-07T07:00:00Z",
      "comments": []
    },
    {
      "id": 65,
      "username": "graphic_design",
      "userAvatar": "https://picsum.photos/seed/user65/100/100",
      "imageUrl": "https://picsum.photos/seed/post65/600/600",
      "caption": "Logo design process 💡",
      "likes": 890,
      "timestamp": "2025-09-07T13:45:00Z",
      "comments": [
        {
          "id": 52,
          "username": "design_studio",
          "text": "Clean design!",
          "timestamp": "2025-09-07T14:30:00Z"
        }
      ]
    },
    {
      "id": 66,
      "username": "sunrise_chaser",
      "userAvatar": "https://picsum.photos/seed/user66/100/100",
      "imageUrl": "https://picsum.photos/seed/post66/600/600",
      "caption": "Another beautiful sunrise 🌅",
      "likes": 2890,
      "timestamp": "2025-09-06T06:15:00Z",
      "comments": [
        {
          "id": 53,
          "username": "early_birds",
          "text": "Worth waking up for!",
          "timestamp": "2025-09-06T07:00:00Z"
        }
      ]
    },
    {
      "id": 67,
      "username": "camping_gear",
      "userAvatar": "https://picsum.photos/seed/user67/100/100",
      "imageUrl": "https://picsum.photos/seed/post67/600/600",
      "caption": "Campsite setup complete ⛺",
      "likes": 1234,
      "timestamp": "2025-09-06T17:30:00Z",
      "comments": []
    },
    {
      "id": 68,
      "username": "pasta_homemade",
      "userAvatar": "https://picsum.photos/seed/user68/100/100",
      "imageUrl": "https://picsum.photos/seed/post68/600/600",
      "caption": "Fresh pasta from scratch 🍝",
      "likes": 1678,
      "timestamp": "2025-09-05T18:00:00Z",
      "comments": [
        {
          "id": 54,
          "username": "italian_food",
          "text": "Looks authentic!",
          "timestamp": "2025-09-05T19:00:00Z"
        }
      ]
    },
    {
      "id": 69,
      "username": "pilates_studio",
      "userAvatar": "https://picsum.photos/seed/user69/100/100",
      "imageUrl": "https://picsum.photos/seed/post69/600/600",
      "caption": "Core strength session 💪",
      "likes": 567,
      "timestamp": "2025-09-05T09:30:00Z",
      "comments": [
        {
          "id": 55,
          "username": "fitness_goals",
          "text": "Great form!",
          "timestamp": "2025-09-05T10:00:00Z"
        }
      ]
    },
    {
      "id": 70,
      "username": "bird_photography",
      "userAvatar": "https://picsum.photos/seed/user70/100/100",
      "imageUrl": "https://picsum.photos/seed/post70/600/600",
      "caption": "Hummingbird in flight 🦜",
      "likes": 3456,
      "timestamp": "2025-09-04T11:00:00Z",
      "comments": [
        {
          "id": 56,
          "username": "wildlife_shots",
          "text": "Perfect timing!",
          "timestamp": "2025-09-04T12:00:00Z"
        }
      ]
    },
    {
      "id": 71,
      "username": "espresso_bar",
      "userAvatar": "https://picsum.photos/seed/user71/100/100",
      "imageUrl": "https://picsum.photos/seed/post71/600/600",
      "caption": "Double espresso shot ☕",
      "likes": 445,
      "timestamp": "2025-09-04T07:30:00Z",
      "comments": []
    },
    {
      "id": 72,
      "username": "landscape_painter",
      "userAvatar": "https://picsum.photos/seed/user72/100/100",
      "imageUrl": "https://picsum.photos/seed/post72/600/600",
      "caption": "Watercolor landscape 🎨",
      "likes": 1123,
      "timestamp": "2025-09-03T15:00:00Z",
      "comments": [
        {
          "id": 57,
          "username": "art_teachers",
          "text": "Beautiful technique!",
          "timestamp": "2025-09-03T16:00:00Z"
        }
      ]
    },
    {
      "id": 73,
      "username": "boxing_fitness",
      "userAvatar": "https://picsum.photos/seed/user73/100/100",
      "imageUrl": "https://picsum.photos/seed/post73/600/600",
      "caption": "Training day 🥊",
      "likes": 890,
      "timestamp": "2025-09-03T18:30:00Z",
      "comments": [
        {
          "id": 58,
          "username": "fight_club",
          "text": "Keep pushing!",
          "timestamp": "2025-09-03T19:00:00Z"
        }
      ]
    },
    {
      "id": 74,
      "username": "road_trip",
      "userAvatar": "https://picsum.photos/seed/user74/100/100",
      "imageUrl": "https://picsum.photos/seed/post74/600/600",
      "caption": "On the road again 🚗",
      "likes": 1890,
      "timestamp": "2025-09-02T10:00:00Z",
      "comments": []
    },
    {
      "id": 75,
      "username": "sourdough_baker",
      "userAvatar": "https://picsum.photos/seed/user75/100/100",
      "imageUrl": "https://picsum.photos/seed/post75/600/600",
      "caption": "Perfect sourdough loaf 🍞",
      "likes": 1567,
      "timestamp": "2025-09-02T08:00:00Z",
      "comments": [
        {
          "id": 59,
          "username": "bread_makers",
          "text": "That crust!",
          "timestamp": "2025-09-02T09:00:00Z"
        }
      ]
    },
    {
      "id": 76,
      "username": "jewelry_maker",
      "userAvatar": "https://picsum.photos/seed/user76/100/100",
      "imageUrl": "https://picsum.photos/seed/post76/600/600",
      "caption": "Handcrafted silver ring 💍",
      "likes": 723,
      "timestamp": "2025-09-01T14:30:00Z",
      "comments": [
        {
          "id": 60,
          "username": "craft_lovers",
          "text": "Gorgeous detail!",
          "timestamp": "2025-09-01T15:00:00Z"
        }
      ]
    },
    {
      "id": 77,
      "username": "tennis_player",
      "userAvatar": "https://picsum.photos/seed/user77/100/100",
      "imageUrl": "https://picsum.photos/seed/post77/600/600",
      "caption": "Match point! 🎾",
      "likes": 1234,
      "timestamp": "2025-09-01T16:00:00Z",
      "comments": []
    },
    {
      "id": 78,
      "username": "stargazing",
      "userAvatar": "https://picsum.photos/seed/user78/100/100",
      "imageUrl": "https://picsum.photos/seed/post78/600/600",
      "caption": "Night sky photography ✨",
      "likes": 2456,
      "timestamp": "2025-08-31T22:30:00Z",
      "comments": [
        {
          "id": 61,
          "username": "astronomy_club",
          "text": "Beautiful capture!",
          "timestamp": "2025-08-31T23:00:00Z"
        }
      ]
    },
    {
      "id": 79,
      "username": "smoothie_bowls",
      "userAvatar": "https://picsum.photos/seed/user79/100/100",
      "imageUrl": "https://picsum.photos/seed/post79/600/600",
      "caption": "Acai bowl perfection 🥣",
      "likes": 945,
      "timestamp": "2025-08-31T09:00:00Z",
      "comments": [
        {
          "id": 62,
          "username": "healthy_breakfast",
          "text": "Yum!",
          "timestamp": "2025-08-31T10:00:00Z"
        }
      ]
    },
    {
      "id": 80,
      "username": "sculpture_art",
      "userAvatar": "https://picsum.photos/seed/user80/100/100",
      "imageUrl": "https://picsum.photos/seed/post80/600/600",
      "caption": "Clay sculpture in progress 🗿",
      "likes": 678,
      "timestamp": "2025-08-30T13:15:00Z",
      "comments": []
    },
    {
      "id": 81,
      "username": "parkour_athlete",
      "userAvatar": "https://picsum.photos/seed/user81/100/100",
      "imageUrl": "https://picsum.photos/seed/post81/600/600",
      "caption": "Urban movement 🏃‍♂️",
      "likes": 1890,
      "timestamp": "2025-08-30T17:00:00Z",
      "comments": [
        {
          "id": 63,
          "username": "freerunning",
          "text": "Smooth moves!",
          "timestamp": "2025-08-30T18:00:00Z"
        }
      ]
    },
    {
      "id": 82,
      "username": "wine_tasting",
      "userAvatar": "https://picsum.photos/seed/user82/100/100",
      "imageUrl": "https://picsum.photos/seed/post82/600/600",
      "caption": "Vineyard visit 🍷",
      "likes": 1456,
      "timestamp": "2025-08-29T16:30:00Z",
      "comments": [
        {
          "id": 64,
          "username": "wine_lovers",
          "text": "Great choice!",
          "timestamp": "2025-08-29T17:00:00Z"
        }
      ]
    },
    {
      "id": 83,
      "username": "drone_racing",
      "userAvatar": "https://picsum.photos/seed/user83/100/100",
      "imageUrl": "https://picsum.photos/seed/post83/600/600",
      "caption": "FPV racing action 🚁",
      "likes": 1234,
      "timestamp": "2025-08-29T14:00:00Z",
      "comments": []
    },
    {
      "id": 84,
      "username": "bonsai_garden",
      "userAvatar": "https://picsum.photos/seed/user84/100/100",
      "imageUrl": "https://picsum.photos/seed/post84/600/600",
      "caption": "20-year-old bonsai tree 🌳",
      "likes": 2134,
      "timestamp": "2025-08-28T10:00:00Z",
      "comments": [
        {
          "id": 65,
          "username": "zen_garden",
          "text": "Stunning patience!",
          "timestamp": "2025-08-28T11:00:00Z"
        }
      ]
    },
    {
      "id": 85,
      "username": "tacos_everyday",
      "userAvatar": "https://picsum.photos/seed/user85/100/100",
      "imageUrl": "https://picsum.photos/seed/post85/600/600",
      "caption": "Taco Tuesday done right 🌮",
      "likes": 1678,
      "timestamp": "2025-08-28T19:00:00Z",
      "comments": [
        {
          "id": 66,
          "username": "mexican_food",
          "text": "Those look authentic!",
          "timestamp": "2025-08-28T20:00:00Z"
        }
      ]
    },
    {
      "id": 86,
      "username": "rock_climbing",
      "userAvatar": "https://picsum.photos/seed/user86/100/100",
      "imageUrl": "https://picsum.photos/seed/post86/600/600",
      "caption": "Outdoor climbing session 🧗",
      "likes": 1890,
      "timestamp": "2025-08-27T12:30:00Z",
      "comments": []
    },
    {
      "id": 87,
      "username": "origami_master",
      "userAvatar": "https://picsum.photos/seed/user87/100/100",
      "imageUrl": "https://picsum.photos/seed/post87/600/600",
      "caption": "Paper crane collection 🦢",
      "likes": 567,
      "timestamp": "2025-08-27T15:00:00Z",
      "comments": [
        {
          "id": 67,
          "username": "paper_art",
          "text": "How long did this take?",
          "timestamp": "2025-08-27T16:00:00Z"
        }
      ]
    },
    {
      "id": 88,
      "username": "sunset_lover",
      "userAvatar": "https://picsum.photos/seed/user88/100/100",
      "imageUrl": "https://picsum.photos/seed/post88/600/600",
      "caption": "Another day, another sunset 🌇",
      "likes": 3890,
      "timestamp": "2025-08-26T19:30:00Z",
      "comments": [
        {
          "id": 68,
          "username": "sky_watchers",
          "text": "Magical colors!",
          "timestamp": "2025-08-26T20:00:00Z"
        }
      ]
    },
    {
      "id": 89,
      "username": "ice_cream_shop",
      "userAvatar": "https://picsum.photos/seed/user89/100/100",
      "imageUrl": "https://picsum.photos/seed/post89/600/600",
      "caption": "Homemade gelato flavors 🍨",
      "likes": 1123,
      "timestamp": "2025-08-26T14:00:00Z",
      "comments": [
        {
          "id": 69,
          "username": "sweet_treats",
          "text": "What flavors?",
          "timestamp": "2025-08-26T15:00:00Z"
        }
      ]
    },
    {
      "id": 90,
      "username": "bmx_tricks",
      "userAvatar": "https://picsum.photos/seed/user90/100/100",
      "imageUrl": "https://picsum.photos/seed/post90/600/600",
      "caption": "New ramp at the park 🚴",
      "likes": 1456,
      "timestamp": "2025-08-25T16:45:00Z",
      "comments": []
    },
    {
      "id": 91,
      "username": "meditation_space",
      "userAvatar": "https://picsum.photos/seed/user91/100/100",
      "imageUrl": "https://picsum.photos/seed/post91/600/600",
      "caption": "My zen corner 🧘‍♀️",
      "likes": 890,
      "timestamp": "2025-08-25T08:00:00Z",
      "comments": [
        {
          "id": 70,
          "username": "mindfulness_daily",
          "text": "So peaceful!",
          "timestamp": "2025-08-25T09:00:00Z"
        }
      ]
    },
    {
      "id": 92,
      "username": "graffiti_artist",
      "userAvatar": "https://picsum.photos/seed/user92/100/100",
      "imageUrl": "https://picsum.photos/seed/post92/600/600",
      "caption": "New mural finished 🎨",
      "likes": 2890,
      "timestamp": "2025-08-24T18:00:00Z",
      "comments": [
        {
          "id": 71,
          "username": "street_art_daily",
          "text": "Incredible work!",
          "timestamp": "2025-08-24T19:00:00Z"
        }
      ]
    },
    {
      "id": 93,
      "username": "pizza_master",
      "userAvatar": "https://picsum.photos/seed/user93/100/100",
      "imageUrl": "https://picsum.photos/seed/post93/600/600",
      "caption": "Wood-fired pizza perfection 🍕",
      "likes": 2456,
      "timestamp": "2025-08-24T20:00:00Z",
      "comments": [
        {
          "id": 72,
          "username": "pizza_lovers",
          "text": "That crust!",
          "timestamp": "2025-08-24T21:00:00Z"
        }
      ]
    },
    {
      "id": 94,
      "username": "aerial_yoga",
      "userAvatar": "https://picsum.photos/seed/user94/100/100",
      "imageUrl": "https://picsum.photos/seed/post94/600/600",
      "caption": "Floating in the air 🎪",
      "likes": 1234,
      "timestamp": "2025-08-23T10:30:00Z",
      "comments": []
    },
    {
      "id": 95,
      "username": "lighthouse_photos",
      "userAvatar": "https://picsum.photos/seed/user95/100/100",
      "imageUrl": "https://picsum.photos/seed/post95/600/600",
      "caption": "Coastal lighthouse at dawn 🗼",
      "likes": 1890,
      "timestamp": "2025-08-23T06:00:00Z",
      "comments": [
        {
          "id": 73,
          "username": "coastal_life",
          "text": "Beautiful location!",
          "timestamp": "2025-08-23T07:00:00Z"
        }
      ]
    },
    {
      "id": 96,
      "username": "succulent_garden",
      "userAvatar": "https://picsum.photos/seed/user96/100/100",
      "imageUrl": "https://picsum.photos/seed/post96/600/600",
      "caption": "Succulent collection growing 🌵",
      "likes": 723,
      "timestamp": "2025-08-22T11:00:00Z",
      "comments": [
        {
          "id": 74,
          "username": "plant_parents",
          "text": "So many varieties!",
          "timestamp": "2025-08-22T12:00:00Z"
        }
      ]
    },
    {
      "id": 97,
      "username": "crossfit_athlete",
      "userAvatar": "https://picsum.photos/seed/user97/100/100",
      "imageUrl": "https://picsum.photos/seed/post97/600/600",
      "caption": "WOD completed! 💪",
      "likes": 1567,
      "timestamp": "2025-08-22T18:00:00Z",
      "comments": []
    },
    {
      "id": 98,
      "username": "aurora_chaser",
      "userAvatar": "https://picsum.photos/seed/user98/100/100",
      "imageUrl": "https://picsum.photos/seed/post98/600/600",
      "caption": "Northern lights dancing 🌌",
      "likes": 4567,
      "timestamp": "2025-08-21T23:00:00Z",
      "comments": [
        {
          "id": 75,
          "username": "night_sky",
          "text": "Once in a lifetime!",
          "timestamp": "2025-08-22T00:00:00Z"
        }
      ]
    },
    {
      "id": 99,
      "username": "ramen_specialist",
      "userAvatar": "https://picsum.photos/seed/user99/100/100",
      "imageUrl": "https://picsum.photos/seed/post99/600/600",
      "caption": "Homemade ramen bowl 🍜",
      "likes": 1890,
      "timestamp": "2025-08-21T19:30:00Z",
      "comments": [
        {
          "id": 76,
          "username": "noodle_lovers",
          "text": "Recipe?",
          "timestamp": "2025-08-21T20:00:00Z"
        }
      ]
    },
    {
      "id": 100,
      "username": "balloon_artist",
      "userAvatar": "https://picsum.photos/seed/user100/100/100",
      "imageUrl": "https://picsum.photos/seed/post100/600/600",
      "caption": "Hot air balloon ride 🎈",
      "likes": 3456,
      "timestamp": "2025-08-21T07:00:00Z",
      "comments": [
        {
          "id": 77,
          "username": "adventure_seekers",
          "text": "Bucket list item!",
          "timestamp": "2025-08-21T08:00:00Z"
        },
        {
          "id": 78,
          "username": "sky_high",
          "text": "What an experience!",
          "timestamp": "2025-08-21T09:00:00Z"
        }
      ]
    }
  ]
}
